{
    "articles": [
        {
            "article_id": "64ad0921e04322743508f78589c9aea0",
            "title": "Trump revokes Biden executive order on addressing AI risks",
            "link": "https://theprint.in/tech/trump-revokes-biden-executive-order-on-addressing-ai-risks/2454676/",
            "keywords": [
                "tech",
                "reuters wire"
            ],
            "creator": [
                "Reuters"
            ],
            "video_url": null,
            "description": "WASHINGTON (Reuters) - U.S. President Donald Trump on Monday revoked a 2023 executive order signed by Joe Biden that sought to reduce the risks that artificial intelligence poses to consumers, workers",
            "content": "ONLY AVAILABLE IN PAID PLANS",
            "pubDate": "2025-01-21 00:15:59",
            "pubDateTZ": "UTC",
            "image_url": null,
            "source_id": "theprint",
            "source_priority": 14094,
            "source_name": "Theprint",
            "source_url": "https://theprint.in",
            "source_icon": "https://i.bytvi.com/domain_icons/theprint.png",
            "language": "english",
            "country": [
                "india"
            ],
            "category": [
                "technology"
            ],
            "ai_tag": "ONLY AVAILABLE IN PROFESSIONAL AND CORPORATE PLANS",
            "sentiment": "ONLY AVAILABLE IN PROFESSIONAL AND CORPORATE PLANS",
            "sentiment_stats": "ONLY AVAILABLE IN PROFESSIONAL AND CORPORATE PLANS",
            "ai_region": "ONLY AVAILABLE IN CORPORATE PLANS",
            "ai_org": "ONLY AVAILABLE IN CORPORATE PLANS",
            "duplicate": true
        },
        {
            "article_id": "c3a9e4abef48962b6f1a1c0bcd2a260b",
            "title": "5 facts on Usha Vance, first Indian-origin second lady of US",
            "link": "https://www.hindustantimes.com/world-news/5-facts-on-usha-vance-first-indian-origin-second-lady-of-us-101737416860078.html",
            "keywords": [
                "latest"
            ],
            "creator": null,
            "video_url": null,
            "description": "Usha Vance became the first Indian-origin second lady of the US as her husband James David Vance took the Vice Presidential oath.",
            "content": "ONLY AVAILABLE IN PAID PLANS",
            "pubDate": "2025-01-21 00:15:51",
            "pubDateTZ": "UTC",
            "image_url": "https://www.hindustantimes.com/ht-img/img/2025/01/20/1600x900/Trump-Inauguration-416_1737417029112_1737417053136.jpg",
            "source_id": "hindustantimes",
            "source_priority": 933,
            "source_name": "Hindustan Times",
            "source_url": "http://www.hindustantimes.com",
            "source_icon": "https://i.bytvi.com/domain_icons/hindustantimes.png",
            "language": "english",
            "country": [
                "india"
            ],
            "category": [
                "top"
            ],
            "ai_tag": "ONLY AVAILABLE IN PROFESSIONAL AND CORPORATE PLANS",
            "sentiment": "ONLY AVAILABLE IN PROFESSIONAL AND CORPORATE PLANS",
            "sentiment_stats": "ONLY AVAILABLE IN PROFESSIONAL AND CORPORATE PLANS",
            "ai_region": "ONLY AVAILABLE IN CORPORATE PLANS",
            "ai_org": "ONLY AVAILABLE IN CORPORATE PLANS",
            "duplicate": false
        },
        {
            "article_id": "a4bd2121bdeeea3f2f25220477623577",
            "title": "Dollar under water on signs Trump tariffs to be gradual",
            "link": "https://theprint.in/economy/dollar-under-water-on-signs-trump-tariffs-to-be-gradual/2454674/",
            "keywords": [
                "economy",
                "reuters wire"
            ],
            "creator": [
                "Reuters"
            ],
            "video_url": null,
            "description": "By Wayne Cole SYDNEY (Reuters) - The dollar nursed broad losses on Tuesday after U.S. President Donald Trump stopped short of imposing new tariffs and reports suggested any new taxes would be imposed",
            "content": "ONLY AVAILABLE IN PAID PLANS",
            "pubDate": "2025-01-21 00:15:40",
            "pubDateTZ": "UTC",
            "image_url": "https://static.theprint.in/wp-content/uploads/2025/01/Dollar_276-696x433.jpg",
            "source_id": "theprint",
            "source_priority": 14094,
            "source_name": "Theprint",
            "source_url": "https://theprint.in",
            "source_icon": "https://i.bytvi.com/domain_icons/theprint.png",
            "language": "english",
            "country": [
                "india"
            ],
            "category": [
                "business"
            ],
            "ai_tag": "ONLY AVAILABLE IN PROFESSIONAL AND CORPORATE PLANS",
            "sentiment": "ONLY AVAILABLE IN PROFESSIONAL AND CORPORATE PLANS",
            "sentiment_stats": "ONLY AVAILABLE IN PROFESSIONAL AND CORPORATE PLANS",
            "ai_region": "ONLY AVAILABLE IN CORPORATE PLANS",
            "ai_org": "ONLY AVAILABLE IN CORPORATE PLANS",
            "duplicate": false
        },
        {
            "article_id": "b8e85e430038d7e92ff01eaa30265ed2",
            "title": "Bigg Boss 18 winner Karan Veer Mehra is ecstatic, as he proudly says, ‘I do not make mistakes, mistakes have made me’",
            "link": "https://www.tribuneindia.com/news/lifestyle/bigg-boss-18-winner-karan-veer-mehra-is-ecstatic-as-he-proudly-says-i-do-not-make-mistakes-mistakes-have-made-me",
            "keywords": null,
            "creator": [
                "Mona"
            ],
            "video_url": null,
            "description": "Yeh trophy meri hai, aur main is trophy ka Karan Veer Mehra... the Bigg Boss 18 winner said loud and clear after a star-studded finale on Sunday. The actor got into Bigg Boss house soon after winning another major reality show, Fear Factor: Khatron Ke Khiladi 14. He claims to have entered the show sans [...]",
            "content": "ONLY AVAILABLE IN PAID PLANS",
            "pubDate": "2025-01-21 00:15:36",
            "pubDateTZ": "UTC",
            "image_url": "https://www.tribuneindia.com/sortd-service/imaginary/v22-01/webp/medium/high?url=dGhldHJpYnVuZS1zb3J0ZC1wcm8tcHJvZC1zb3J0ZC9tZWRpYWRhNWM5YWIwLWQ3OGMtMTFlZi04ZGU2LTkzNGIzY2M4YTM2NC5qcGc%3D",
            "source_id": "tribuneindia",
            "source_priority": 15316,
            "source_name": "The Tribune India",
            "source_url": "https://www.tribuneindia.com",
            "source_icon": "https://i.bytvi.com/domain_icons/tribuneindia.png",
            "language": "english",
            "country": [
                "india"
            ],
            "category": [
                "lifestyle"
            ],
            "ai_tag": "ONLY AVAILABLE IN PROFESSIONAL AND CORPORATE PLANS",
            "sentiment": "ONLY AVAILABLE IN PROFESSIONAL AND CORPORATE PLANS",
            "sentiment_stats": "ONLY AVAILABLE IN PROFESSIONAL AND CORPORATE PLANS",
            "ai_region": "ONLY AVAILABLE IN CORPORATE PLANS",
            "ai_org": "ONLY AVAILABLE IN CORPORATE PLANS",
            "duplicate": false
        },
        {
            "article_id": "b5cc168c5e92039739724fb28950f9be",
            "title": "Cowboys meet with Leslie Frazier, 3rd external interview in search to replace Mike McCarthy",
            "link": "https://www.hindustantimes.com/sports/cowboys-meet-with-leslie-frazier-3rd-external-interview-in-search-to-replace-mike-mccarthy-101737418530776.html",
            "keywords": [
                "latest"
            ],
            "creator": null,
            "video_url": null,
            "description": "Cowboys meet with Leslie Frazier, 3rd external interview in search to replace Mike McCarthy",
            "content": "ONLY AVAILABLE IN PAID PLANS",
            "pubDate": "2025-01-21 00:15:30",
            "pubDateTZ": "UTC",
            "image_url": "https://images.hindustantimes.com/default/1600x900.jpg",
            "source_id": "hindustantimes",
            "source_priority": 933,
            "source_name": "Hindustan Times",
            "source_url": "http://www.hindustantimes.com",
            "source_icon": "https://i.bytvi.com/domain_icons/hindustantimes.png",
            "language": "english",
            "country": [
                "india"
            ],
            "category": [
                "top"
            ],
            "ai_tag": "ONLY AVAILABLE IN PROFESSIONAL AND CORPORATE PLANS",
            "sentiment": "ONLY AVAILABLE IN PROFESSIONAL AND CORPORATE PLANS",
            "sentiment_stats": "ONLY AVAILABLE IN PROFESSIONAL AND CORPORATE PLANS",
            "ai_region": "ONLY AVAILABLE IN CORPORATE PLANS",
            "ai_org": "ONLY AVAILABLE IN CORPORATE PLANS",
            "duplicate": true
        },
        {
            "article_id": "26398a6ad227132b037f6e2ae9845b72",
            "title": "Senate Foreign Relations Committee approves Marco Rubio's nomination for Secretary of State",
            "link": "https://in.investing.com/news/world-news/senate-foreign-relations-committee-approves-marco-rubios-nomination-for-secretary-of-state-4620679",
            "keywords": null,
            "creator": [
                "IANS"
            ],
            "video_url": null,
            "description": null,
            "content": "ONLY AVAILABLE IN PAID PLANS",
            "pubDate": "2025-01-21 00:15:17",
            "pubDateTZ": "UTC",
            "image_url": "https://i-invdn-com.investing.com/news/news_headline_open_108x81.jpg",
            "source_id": "investing_in",
            "source_priority": 1205,
            "source_name": "Investing India",
            "source_url": "https://in.investing.com",
            "source_icon": null,
            "language": "english",
            "country": [
                "india"
            ],
            "category": [
                "top"
            ],
            "ai_tag": "ONLY AVAILABLE IN PROFESSIONAL AND CORPORATE PLANS",
            "sentiment": "ONLY AVAILABLE IN PROFESSIONAL AND CORPORATE PLANS",
            "sentiment_stats": "ONLY AVAILABLE IN PROFESSIONAL AND CORPORATE PLANS",
            "ai_region": "ONLY AVAILABLE IN CORPORATE PLANS",
            "ai_org": "ONLY AVAILABLE IN CORPORATE PLANS",
            "duplicate": false
        },
        {
            "article_id": "c9f43e508c0ac2b50607a64d16487dda",
            "title": "Marco Rubio confirmed as Secretary of State, first Trump Cabinet official to be approved (Ld)",
            "link": "https://in.investing.com/news/world-news/marco-rubio-confirmed-as-secretary-of-state-first-trump-cabinet-official-to-be-approved-ld-4620678",
            "keywords": null,
            "creator": [
                "IANS"
            ],
            "video_url": null,
            "description": null,
            "content": "ONLY AVAILABLE IN PAID PLANS",
            "pubDate": "2025-01-21 00:15:15",
            "pubDateTZ": "UTC",
            "image_url": null,
            "source_id": "investing_in",
            "source_priority": 1205,
            "source_name": "Investing India",
            "source_url": "https://in.investing.com",
            "source_icon": null,
            "language": "english",
            "country": [
                "india"
            ],
            "category": [
                "top"
            ],
            "ai_tag": "ONLY AVAILABLE IN PROFESSIONAL AND CORPORATE PLANS",
            "sentiment": "ONLY AVAILABLE IN PROFESSIONAL AND CORPORATE PLANS",
            "sentiment_stats": "ONLY AVAILABLE IN PROFESSIONAL AND CORPORATE PLANS",
            "ai_region": "ONLY AVAILABLE IN CORPORATE PLANS",
            "ai_org": "ONLY AVAILABLE IN CORPORATE PLANS",
            "duplicate": false
        },
        {
            "article_id": "7cce6fd93252440ca85318e6f6e1b798",
            "title": "Fresh US sanctions on Russian oil may hit GRMs of Indian refiners",
            "link": "https://www.livemint.com/industry/fresh-us-sanctions-on-russian-oil-may-hit-grms-of-indian-refiners-petroleum-11737375864514.html",
            "keywords": null,
            "creator": null,
            "video_url": null,
            "description": "As Russian discounts fall to below $5 per barrel, GRMs of India public sector OMCs have already declined by about 80% in FY25 from the highs recorded in FY24.",
            "content": "ONLY AVAILABLE IN PAID PLANS",
            "pubDate": "2025-01-21 00:15:11",
            "pubDateTZ": "UTC",
            "image_url": "https://www.livemint.com/lm-img/img/2025/01/20/1600x900/TEXAS-OIL-6_1734739054823_1737404955917.jpg",
            "source_id": "livemint",
            "source_priority": 7134,
            "source_name": "Mint",
            "source_url": "https://www.livemint.com",
            "source_icon": "https://i.bytvi.com/domain_icons/livemint.png",
            "language": "english",
            "country": [
                "india"
            ],
            "category": [
                "business"
            ],
            "ai_tag": "ONLY AVAILABLE IN PROFESSIONAL AND CORPORATE PLANS",
            "sentiment": "ONLY AVAILABLE IN PROFESSIONAL AND CORPORATE PLANS",
            "sentiment_stats": "ONLY AVAILABLE IN PROFESSIONAL AND CORPORATE PLANS",
            "ai_region": "ONLY AVAILABLE IN CORPORATE PLANS",
            "ai_org": "ONLY AVAILABLE IN CORPORATE PLANS",
            "duplicate": false
        },
        {
            "article_id": "dc889b1c74fd43307808954a092ff601",
            "title": "Seven stocks to buy and sell today — 21 January",
            "link": "https://www.livemint.com/market/stock-market-news/stocks-recommendations-ankush-bajaj-marketsmith-raja-venkatraman-stocks-to-buy-redington-biocon-laurus-labs-11737382263124.html",
            "keywords": null,
            "creator": null,
            "video_url": null,
            "description": "Here's a list of buy/sell recommendations for today from three analysts: Ankush Bajaj, Raja Venkatraman, and MarketSmith India.",
            "content": "ONLY AVAILABLE IN PAID PLANS",
            "pubDate": "2025-01-21 00:15:11",
            "pubDateTZ": "UTC",
            "image_url": "https://www.livemint.com/lm-img/img/2025/01/20/1600x900/investment_1731737985428_1737382734982.PNG",
            "source_id": "livemint",
            "source_priority": 7134,
            "source_name": "Mint",
            "source_url": "https://www.livemint.com",
            "source_icon": "https://i.bytvi.com/domain_icons/livemint.png",
            "language": "english",
            "country": [
                "india"
            ],
            "category": [
                "business"
            ],
            "ai_tag": "ONLY AVAILABLE IN PROFESSIONAL AND CORPORATE PLANS",
            "sentiment": "ONLY AVAILABLE IN PROFESSIONAL AND CORPORATE PLANS",
            "sentiment_stats": "ONLY AVAILABLE IN PROFESSIONAL AND CORPORATE PLANS",
            "ai_region": "ONLY AVAILABLE IN CORPORATE PLANS",
            "ai_org": "ONLY AVAILABLE IN CORPORATE PLANS",
            "duplicate": false
        },
        {
            "article_id": "6a716d09b3b32ac18bc74e53f422d90c",
            "title": "Stocks to buy: Ankush Bajaj recommends two stocks for today—21 January",
            "link": "https://www.livemint.com/market/stock-market-news/stocks-to-buy-ankush-bajaj-stocks-stock-recommendations-21-january-nifty-50-nifty-bank-redington-ltd-biocon-ltd-11737379971198.html",
            "keywords": null,
            "creator": null,
            "video_url": null,
            "description": "Here are two stocks to buy as recommended by research analyst Ankush Bajaj for 21 January.",
            "content": "ONLY AVAILABLE IN PAID PLANS",
            "pubDate": "2025-01-21 00:15:11",
            "pubDateTZ": "UTC",
            "image_url": "https://www.livemint.com/lm-img/img/2025/01/20/1600x900/Screenshot_2025-01-09_181715_1736426865930_1737380005661.png",
            "source_id": "livemint",
            "source_priority": 7134,
            "source_name": "Mint",
            "source_url": "https://www.livemint.com",
            "source_icon": "https://i.bytvi.com/domain_icons/livemint.png",
            "language": "english",
            "country": [
                "india"
            ],
            "category": [
                "business"
            ],
            "ai_tag": "ONLY AVAILABLE IN PROFESSIONAL AND CORPORATE PLANS",
            "sentiment": "ONLY AVAILABLE IN PROFESSIONAL AND CORPORATE PLANS",
            "sentiment_stats": "ONLY AVAILABLE IN PROFESSIONAL AND CORPORATE PLANS",
            "ai_region": "ONLY AVAILABLE IN CORPORATE PLANS",
            "ai_org": "ONLY AVAILABLE IN CORPORATE PLANS",
            "duplicate": false
        },
        {
            "article_id": "6c5995a7bb3da0b642a25e7eb17146da",
            "title": "21 January ka Kark Tarot Card: कर्क राशि वालों का जीवन आनंदमय बना रहेगा, नए लोगों से होगी मुलाकात",
            "link": "https://www.tv9hindi.com/religion/rashiphal/today-cancer-tarot-card-reading-21-january-2025-tuesday-tarot-prediction-horoscope-in-hindi-3069917.html",
            "keywords": null,
            "creator": [
                "Arunesh Kumar"
            ],
            "video_url": null,
            "description": "Daily Tarot Card Prediction : कर्क राशि वाले लोगों के प्रति पूर्वाग्रह से बचें. अपनों संग खुशियों पर जोर बनाए रखेंगे. सूझबूझ से विभिन्न निर्णय लेंगे. व्यवस्था पर नियंत्रण बढाएंगे.",
            "content": "ONLY AVAILABLE IN PAID PLANS",
            "pubDate": "2025-01-21 00:15:07",
            "pubDateTZ": "UTC",
            "image_url": "https://images.tv9hindi.com/wp-content/uploads/2024/12/tarot-3.jpeg",
            "source_id": "tv9bharatvarsh",
            "source_priority": 40538658,
            "source_name": "Tv9 Bharatvarsh",
            "source_url": "https://www.tv9hindi.com",
            "source_icon": null,
            "language": "hindi",
            "country": [
                "india"
            ],
            "category": [
                "top"
            ],
            "ai_tag": "ONLY AVAILABLE IN PROFESSIONAL AND CORPORATE PLANS",
            "sentiment": "ONLY AVAILABLE IN PROFESSIONAL AND CORPORATE PLANS",
            "sentiment_stats": "ONLY AVAILABLE IN PROFESSIONAL AND CORPORATE PLANS",
            "ai_region": "ONLY AVAILABLE IN CORPORATE PLANS",
            "ai_org": "ONLY AVAILABLE IN CORPORATE PLANS",
            "duplicate": false
        },
        {
            "article_id": "a6f2ba76fc719120558d688b0b1890fe",
            "title": "आज का अंक ज्योतिष 21 जनवरी : गुरु की कृपा से मूलांक 3 वाले लोग अपने विचारों से कामयाबी और सराहना पाएंगे, जन्मतिथि से जानें आज कैसा रहेगा आपका दिन",
            "link": "https://navbharattimes.indiatimes.com/astro/rashifal/numerology-prediction/numerology-prediction-21-january-2025-numerology-3-people-will-get-success-from-their-opinion-know-today-numerology-prediction-according-to-your-birthdate/articleshow/117398030.cms",
            "keywords": null,
            "creator": null,
            "video_url": null,
            "description": "Aaj Ka Ank Jyotish, 21 January 2025 : आज 21 जनवरी 2025, मंगलवार का दिन हनुमान जी को समर्पित होता है। अंक ज्योतिष भविष्यफल के अनुसार आज जिनका जन्मदिन है, उनका मूलांक 3 होगा। मूलांक 3 के स्वामी गुरु हैं। आज के अंक ज्योतिष भविष्यफल के अनुसार मूलांक 3 वाले लोग अपने विचारों से तरक्की पाएंगे। आइए, विस्तार से जानते हैं कि आज कैसा रहेगा मूलांक 1 से मूलांक 9 तक का दिन।",
            "content": "ONLY AVAILABLE IN PAID PLANS",
            "pubDate": "2025-01-21 00:15:00",
            "pubDateTZ": "UTC",
            "image_url": "https://static.langimg.com/photo/imgsize-3727754,msid-117398030/navbharat-times.jpg",
            "source_id": "navbharattimes",
            "source_priority": 244,
            "source_name": "Nbt Navbharattimes",
            "source_url": "https://navbharattimes.indiatimes.com",
            "source_icon": "https://i.bytvi.com/domain_icons/navbharattimes.png",
            "language": "hindi",
            "country": [
                "india"
            ],
            "category": [
                "other"
            ],
            "ai_tag": "ONLY AVAILABLE IN PROFESSIONAL AND CORPORATE PLANS",
            "sentiment": "ONLY AVAILABLE IN PROFESSIONAL AND CORPORATE PLANS",
            "sentiment_stats": "ONLY AVAILABLE IN PROFESSIONAL AND CORPORATE PLANS",
            "ai_region": "ONLY AVAILABLE IN CORPORATE PLANS",
            "ai_org": "ONLY AVAILABLE IN CORPORATE PLANS",
            "duplicate": false
        },
        {
            "article_id": "f2763dbcf9d6cfac5972a565eb0cccf7",
            "title": "Tragedy Strikes: Infant Passes Away Mid-Flight to Kerala",
            "link": "https://www.devdiscourse.com/article/health/3232870-tragedy-strikes-infant-passes-away-mid-flight-to-kerala",
            "keywords": null,
            "creator": [
                "noemail@noemail.org (Devdiscourse News Desk)"
            ],
            "video_url": null,
            "description": "An infant's life ended in tragedy as he succumbed to health complications while aboard a Kerala-bound flight from Qatar. The 11-month-old, named Fesin Ahammed, was en route to the southern Indian state for critical medical treatment.",
            "content": "ONLY AVAILABLE IN PAID PLANS",
            "pubDate": "2025-01-21 00:14:52",
            "pubDateTZ": "UTC",
            "image_url": "https://devdiscourse.blob.core.windows.net/devnews/23_12_2023_17_01_50_3955928.jpg",
            "source_id": "devdiscourse",
            "source_priority": 566021,
            "source_name": "Devdiscourse",
            "source_url": "https://www.devdiscourse.com",
            "source_icon": "https://i.bytvi.com/domain_icons/devdiscourse.jpg",
            "language": "english",
            "country": [
                "india"
            ],
            "category": [
                "top"
            ],
            "ai_tag": "ONLY AVAILABLE IN PROFESSIONAL AND CORPORATE PLANS",
            "sentiment": "ONLY AVAILABLE IN PROFESSIONAL AND CORPORATE PLANS",
            "sentiment_stats": "ONLY AVAILABLE IN PROFESSIONAL AND CORPORATE PLANS",
            "ai_region": "ONLY AVAILABLE IN CORPORATE PLANS",
            "ai_org": "ONLY AVAILABLE IN CORPORATE PLANS",
            "duplicate": false
        },
        {
            "article_id": "ce5a4cc84c00d5b96dcb4a4caa8611c6",
            "title": "3 held near Tirunelveli for Kotekar cooperative society robbery",
            "link": "https://www.deccanherald.com/india/karnataka/3-held-near-tirunelveli-for-kotekar-cooperative-society-robbery-3364907",
            "keywords": null,
            "creator": [
                "Naina J A"
            ],
            "video_url": null,
            "description": null,
            "content": "ONLY AVAILABLE IN PAID PLANS",
            "pubDate": "2025-01-21 00:14:46",
            "pubDateTZ": "UTC",
            "image_url": "https://images.deccanherald.com/deccanherald%2F2025-01-21%2Fkg0ivdm5%2Farrestistock_1243407_1691050568.jpg?ar=40%3A21&auto=format%2Ccompress&mode=crop&ogImage=true&rect=0%2C27%2C700%2C368&w=1200",
            "source_id": "deccanherald",
            "source_priority": 10080,
            "source_name": "Deccan Herald",
            "source_url": "https://www.deccanherald.com",
            "source_icon": null,
            "language": "english",
            "country": [
                "india"
            ],
            "category": [
                "top"
            ],
            "ai_tag": "ONLY AVAILABLE IN PROFESSIONAL AND CORPORATE PLANS",
            "sentiment": "ONLY AVAILABLE IN PROFESSIONAL AND CORPORATE PLANS",
            "sentiment_stats": "ONLY AVAILABLE IN PROFESSIONAL AND CORPORATE PLANS",
            "ai_region": "ONLY AVAILABLE IN CORPORATE PLANS",
            "ai_org": "ONLY AVAILABLE IN CORPORATE PLANS",
            "duplicate": false
        },
        {
            "article_id": "f5b3f18f79aa1150852ce8f4e952d472",
            "title": "महाकुंभ में तैरता पत्थर देखने आ रहे श्रद्धालु:जूना अखाड़ा के नागा संन्यासी बोले-नल और नील ने रामसेतु में किया था इस्तेमाल",
            "link": "https://www.bhaskar.com/local/uttar-pradesh/news/mahakumbh-2025-floating-stone-juna-akhara-brihaspati-giri-maharaj-134330423.html",
            "keywords": null,
            "creator": null,
            "video_url": null,
            "description": "अध्यात्म, आस्था और विश्वास से भरी महाकुंभ की पवित्र नगरी इन दिनों साधु-संतों और श्रद्धालुओं से गुंजायमान है। जूना अखाड़ा के नागा संन्यासी बृहस्पति गिरी महाराज एक पत्थर रखे हुए हैं, जिसकी खासियत है कि वह पानी में तैरता है। महाराज बताते हैं कि- यह वही पत्थर है, जिसका इस्तेमाल त्रेतायुग में नल और नील ने समुद्र में रामेश्वरम सेतु बनाने के लिए किया था। इस पत्थर पर ‘श्रीराम’ लिखा है। महाकुंभ मेला क्षेत्र में यह पत्थर श्रद्धालुओं के आकर्षण का मुख्य केंद्र बना हुआ है। हर दिन हजारों श्रद्धालु इस पत्थर के दर्शन के लिए आ रहे हैं। दर्शन कर श्रद्धालु न केवल सिर झुकाते हैं, बल्कि अपनी सामर्थ्य अनुसार दान भी करते हैं। देखें वीडियो....",
            "content": "ONLY AVAILABLE IN PAID PLANS",
            "pubDate": "2025-01-21 00:14:43",
            "pubDateTZ": "UTC",
            "image_url": "https://images.bhaskarassets.com/thumb/1000x1000/web2images/521/2025/01/20/comp-41_1737377710.gif",
            "source_id": "bhaskar_hindi",
            "source_priority": 34179,
            "source_name": "Bhaskar",
            "source_url": "https://www.bhaskar.com",
            "source_icon": "https://i.bytvi.com/domain_icons/bhaskar_hindi.png",
            "language": "hindi",
            "country": [
                "india"
            ],
            "category": [
                "top",
                "domestic"
            ],
            "ai_tag": "ONLY AVAILABLE IN PROFESSIONAL AND CORPORATE PLANS",
            "sentiment": "ONLY AVAILABLE IN PROFESSIONAL AND CORPORATE PLANS",
            "sentiment_stats": "ONLY AVAILABLE IN PROFESSIONAL AND CORPORATE PLANS",
            "ai_region": "ONLY AVAILABLE IN CORPORATE PLANS",
            "ai_org": "ONLY AVAILABLE IN CORPORATE PLANS",
            "duplicate": false
        },
        {
            "article_id": "0d3de1047ab868d149eb4e6718ee4449",
            "title": "India News | Union Minister Jyotiraditya Scindia Releases Special Postcard to Mark Completion of 75 Years of Constitution",
            "link": "https://www.latestly.com/agency-news/india-news-union-minister-jyotiraditya-scindia-releases-special-postcard-to-mark-completion-of-75-years-of-constitution-6580969.html",
            "keywords": null,
            "creator": null,
            "video_url": null,
            "description": "Get latest articles and stories on India at LatestLY. Union Minister Jyotiraditya Scindia on Monday released a special postcard issued by India Post Office on the journey of 75 years of the Indian Republic and Constitution.",
            "content": "ONLY AVAILABLE IN PAID PLANS",
            "pubDate": "2025-01-21 00:14:31",
            "pubDateTZ": "UTC",
            "image_url": "https://st1.latestly.com/wp-content/uploads/2025/01/ANI-20250120225940-380x214.jpg",
            "source_id": "latestly",
            "source_priority": 31923,
            "source_name": "Latestly",
            "source_url": "https://www.latestly.com",
            "source_icon": "https://i.bytvi.com/domain_icons/latestly.png",
            "language": "english",
            "country": [
                "india"
            ],
            "category": [
                "top"
            ],
            "ai_tag": "ONLY AVAILABLE IN PROFESSIONAL AND CORPORATE PLANS",
            "sentiment": "ONLY AVAILABLE IN PROFESSIONAL AND CORPORATE PLANS",
            "sentiment_stats": "ONLY AVAILABLE IN PROFESSIONAL AND CORPORATE PLANS",
            "ai_region": "ONLY AVAILABLE IN CORPORATE PLANS",
            "ai_org": "ONLY AVAILABLE IN CORPORATE PLANS",
            "duplicate": false
        },
        {
            "article_id": "3f56ffeacbe3ef39e81b0abdd3fed072",
            "title": "Nancy Pelosi sells Apple, Nvidia stock; Buys Alphabet, Amazon calls, filing shows",
            "link": "https://in.investing.com/news/stock-market-news/nancy-pelosi-sells-apple-nvidia-stock-buys-alphabet-amazon-calls-filing-shows-4620677",
            "keywords": null,
            "creator": [
                "Investing.com"
            ],
            "video_url": null,
            "description": null,
            "content": "ONLY AVAILABLE IN PAID PLANS",
            "pubDate": "2025-01-21 00:14:06",
            "pubDateTZ": "UTC",
            "image_url": null,
            "source_id": "investing_in",
            "source_priority": 1205,
            "source_name": "Investing India",
            "source_url": "https://in.investing.com",
            "source_icon": null,
            "language": "english",
            "country": [
                "india"
            ],
            "category": [
                "business"
            ],
            "ai_tag": "ONLY AVAILABLE IN PROFESSIONAL AND CORPORATE PLANS",
            "sentiment": "ONLY AVAILABLE IN PROFESSIONAL AND CORPORATE PLANS",
            "sentiment_stats": "ONLY AVAILABLE IN PROFESSIONAL AND CORPORATE PLANS",
            "ai_region": "ONLY AVAILABLE IN CORPORATE PLANS",
            "ai_org": "ONLY AVAILABLE IN CORPORATE PLANS",
            "duplicate": true
        },
        {
            "article_id": "85ba6984865668d5f7e7e24938ba9bab",
            "title": "India and Belgium Strengthen Trade Ties with New Mechanisms",
            "link": "https://www.devdiscourse.com/article/business/3232869-india-and-belgium-strengthen-trade-ties-with-new-mechanisms",
            "keywords": null,
            "creator": [
                "noemail@noemail.org (Devdiscourse News Desk)"
            ],
            "video_url": null,
            "description": "India and Belgium have agreed to establish new mechanisms aimed at resolving trade issues specifically within the areas of pharmaceuticals and agricultural products. This initiative was announced following a high-level meeting between India's Commerce and Industry Minister, Piyush Goyal, and Belgium's Minister of Foreign Affairs and Foreign Trade, Bernard Quintin, held in Brussels.",
            "content": "ONLY AVAILABLE IN PAID PLANS",
            "pubDate": "2025-01-21 00:14:02",
            "pubDateTZ": "UTC",
            "image_url": "https://devdiscourse.blob.core.windows.net/devnews/06_01_2024_16_30_12_3566991.jpg",
            "source_id": "devdiscourse",
            "source_priority": 566021,
            "source_name": "Devdiscourse",
            "source_url": "https://www.devdiscourse.com",
            "source_icon": "https://i.bytvi.com/domain_icons/devdiscourse.jpg",
            "language": "english",
            "country": [
                "india"
            ],
            "category": [
                "top"
            ],
            "ai_tag": "ONLY AVAILABLE IN PROFESSIONAL AND CORPORATE PLANS",
            "sentiment": "ONLY AVAILABLE IN PROFESSIONAL AND CORPORATE PLANS",
            "sentiment_stats": "ONLY AVAILABLE IN PROFESSIONAL AND CORPORATE PLANS",
            "ai_region": "ONLY AVAILABLE IN CORPORATE PLANS",
            "ai_org": "ONLY AVAILABLE IN CORPORATE PLANS",
            "duplicate": false
        },
        {
            "article_id": "257709620ae3d3990d393c6117f1828f",
            "title": "Donald Trump Inauguration: List Of Executive Orders Signed At Capitol One Arena",
            "link": "https://www.timesnownews.com/world/us/us-news/donald-trump-inauguration-list-of-executive-orders-signed-at-capitol-one-arena-article-117410491",
            "keywords": null,
            "creator": [
                "Arkaprovo Roy"
            ],
            "video_url": null,
            "description": "In the Capital One Arena, Donald Trump took a seat at a desk and signed what appeared to be a large number of executive orders. 78 executive acts, executive orders, presidential memoranda, and other documents from the Biden administration were revoked in the first order. When Trump mentioned Joe Biden's last-minute pardons for family members, the audience erupted in loud jeering.",
            "content": "ONLY AVAILABLE IN PAID PLANS",
            "pubDate": "2025-01-21 00:13:50",
            "pubDateTZ": "UTC",
            "image_url": "https://static.tnn.in/thumb/msid-117410484,thumbsize-35108,width-1280,height-720,resizemode-75/117410484.jpg",
            "source_id": "timesnownews",
            "source_priority": 2243,
            "source_name": "Times Now News",
            "source_url": "https://www.timesnownews.com",
            "source_icon": "https://i.bytvi.com/domain_icons/timesnownews.png",
            "language": "english",
            "country": [
                "india"
            ],
            "category": [
                "top"
            ],
            "ai_tag": "ONLY AVAILABLE IN PROFESSIONAL AND CORPORATE PLANS",
            "sentiment": "ONLY AVAILABLE IN PROFESSIONAL AND CORPORATE PLANS",
            "sentiment_stats": "ONLY AVAILABLE IN PROFESSIONAL AND CORPORATE PLANS",
            "ai_region": "ONLY AVAILABLE IN CORPORATE PLANS",
            "ai_org": "ONLY AVAILABLE IN CORPORATE PLANS",
            "duplicate": false
        },
        {
            "article_id": "fb42d688f825bb8e0fc76fc490311f38",
            "title": "Churu News: लद्दाख में शहीद हुआ चुरू का बहादुर जावन, पेट्रोलिंग के दौरान द्रास ग्लेशियर में हुआ हादसा...",
            "link": "https://zeenews.india.com/hindi/india/rajasthan/churu/churu-army-jawan-satish-kumar-swami-martyred-in-ladakh-during-patrolling-in-dras-glacier/2610129",
            "keywords": null,
            "creator": [
                "Zee News Hindi"
            ],
            "video_url": null,
            "description": "Churu News: चूरू जिले के ठिमाऊ बड़ी गांव के रहने वाले सतीश कुमार स्वामी ने देश की सेवा में अपनी जान न्योछावर कर दी. वह लद्दाख में ड्यूटी के दौरान शहीद हो गए. सतीश कुमार स्वामी 5 साल पहले सेना में भर्ती हुए थे और गोरखा राइफल रेजिमेंट (फ्रंटियर फोर्स) में नायक के पद पर तैनात थे. उनकी शहादत पर पूरे देश को गर्व है.",
            "content": "ONLY AVAILABLE IN PAID PLANS",
            "pubDate": "2025-01-21 00:13:38",
            "pubDateTZ": "UTC",
            "image_url": "https://hindi.cdn.zeenews.com/hindi/sites/default/files/2025/01/21/3612488-rajasthan-2025-01-21t054322.655.png?im=FitAndFill%3D%281200%2C900%29",
            "source_id": "zeenews",
            "source_priority": 5319,
            "source_name": "Zee News",
            "source_url": "http://zeenews.india.com",
            "source_icon": "https://i.bytvi.com/domain_icons/zeenews.png",
            "language": "hindi",
            "country": [
                "india"
            ],
            "category": [
                "top"
            ],
            "ai_tag": "ONLY AVAILABLE IN PROFESSIONAL AND CORPORATE PLANS",
            "sentiment": "ONLY AVAILABLE IN PROFESSIONAL AND CORPORATE PLANS",
            "sentiment_stats": "ONLY AVAILABLE IN PROFESSIONAL AND CORPORATE PLANS",
            "ai_region": "ONLY AVAILABLE IN CORPORATE PLANS",
            "ai_org": "ONLY AVAILABLE IN CORPORATE PLANS",
            "duplicate": false
        }
    ]
}